wanpy/__init__.py
wanpy/MPI/MPI.py
wanpy/MPI/__init__.py
wanpy/MPI/config.py
wanpy/MPI/config.toml
wanpy/MPI/init_data.py
wanpy/core/__init__.py
wanpy/core/bz.py
wanpy/core/db_msg.py
wanpy/core/errorhandler.py
wanpy/core/greenfunc.py
wanpy/core/mesh.py
wanpy/core/plot.py
wanpy/core/structure.py
wanpy/core/symmetry.py
wanpy/core/toolkits.py
wanpy/core/trans_hr.py
wanpy/core/units.py
wanpy/core/utils.py
wanpy/interface/__init__.py
wanpy/interface/buildwannier.py
wanpy/interface/vasp.py
wanpy/interface/wannier90.py
wanpy/interface/qe/pwscf.py
wanpy/model/BHZ.py
wanpy/model/BiH.py
wanpy/model/__init__.py
wanpy/model/graphene.py
wanpy/model/hydrogen.py
wanpy/model/kp_SurfaceState.py
wanpy/model/kpmodel.py
wanpy/model/rice_mele.py
wanpy/response/__init__.py
wanpy/response/response.py
wanpy/response/topoinvariant.py
wanpy/response/utils.py
wanpy/response/F90/greenTB.f90
wanpy/response/F90/makefile
wanpy/response/F90/md.f90
wanpy/response/F90/nlo.f90
wanpy/response/F90/test.f90
wanpy/scripts/__init__.py
wanpy/scripts/findmsg.py
wanpy/scripts/postinstall.py
wanpy/scripts/statistic_cores.py
wanpy/scripts/wanpy.py
wanpy/scripts/wpyplotband.py
wanpyProjects/__init__.py
wanpyProjects/demo/main.py
wanpyProjects/demo/plot.py
wanpyProjects/demo/lib/config.toml
wanpyProjects/demo/lib/libplot.py
wanpyProjects/demo/lib/libwtb.py
wanpy-0.16.2.dist-info/METADATA
wanpy-0.16.2.dist-info/WHEEL
wanpy-0.16.2.dist-info/entry_points.txt
wanpy-0.16.2.dist-info/licenses/LICENSE
wanpy-0.16.2.dist-info/RECORD
