Metadata-Version: 2.4
Name: wanpy
Version: 0.16.2
Summary: A Wannier Tight-Binding Model Based Numerical Package
Author-email: Jin Cao <caojin.phy@gmail.com>
License:                     GNU GENERAL PUBLIC LICENSE
License-File: LICENSE
Classifier: License :: OSI Approved :: GNU General Public License v3 (GPLv3)
Classifier: Operating System :: OS Independent
Classifier: Programming Language :: Python :: 3
Classifier: Topic :: Scientific/Engineering :: Physics
Requires-Python: >=3.11
Requires-Dist: fortio
Requires-Dist: h5py
Requires-Dist: hatch
Requires-Dist: matplotlib
Requires-Dist: mpi4py
Requires-Dist: numpy
Requires-Dist: pandas
Requires-Dist: scipy
Requires-Dist: spglib>=2.3.0
Requires-Dist: sympy
